setup.py
clixbuild/__init__.py
clixbuild/build.py
clixbuild/clixconfig.py
clixbuild.egg-info/PKG-INFO
clixbuild.egg-info/SOURCES.txt
clixbuild.egg-info/dependency_links.txt
clixbuild.egg-info/entry_points.txt
clixbuild.egg-info/requires.txt
clixbuild.egg-info/top_level.txt