Metadata-Version: 1.0
Name: clixbuild
Version: 1.2.3
Summary: ClixBuild, here to make your troubles vanish, your teeth whiter, and your .htaccess problem disappear
Home-page: http://silassnider.com
Author: Silas Snider
Author-email: silas.snider@showclix.com
License: UNKNOWN
Platform: UNKNOWN
